jupyterlab_citation_data
